awslabs/__init__.py
awslabs/aws_pricing_mcp_server/__init__.py
awslabs/aws_pricing_mcp_server/alternative_pricing.py
awslabs/aws_pricing_mcp_server/cdk_analyzer.py
awslabs/aws_pricing_mcp_server/consts.py
awslabs/aws_pricing_mcp_server/helpers.py
awslabs/aws_pricing_mcp_server/models.py
awslabs/aws_pricing_mcp_server/pricing_client.py
awslabs/aws_pricing_mcp_server/pricing_transformer.py
awslabs/aws_pricing_mcp_server/report_generator.py
awslabs/aws_pricing_mcp_server/server.py
awslabs/aws_pricing_mcp_server/terraform_analyzer.py
awslabs/aws_pricing_mcp_server/static/COST_REPORT_TEMPLATE.md
awslabs/aws_pricing_mcp_server/static/__init__.py
awslabs/aws_pricing_mcp_server/static/patterns/BEDROCK.md
awslabs/aws_pricing_mcp_server/static/patterns/__init__.py
awslabs_aws_pricing_mcp_server-1.0.22.dist-info/METADATA
awslabs_aws_pricing_mcp_server-1.0.22.dist-info/WHEEL
awslabs_aws_pricing_mcp_server-1.0.22.dist-info/entry_points.txt
awslabs_aws_pricing_mcp_server-1.0.22.dist-info/licenses/LICENSE
awslabs_aws_pricing_mcp_server-1.0.22.dist-info/licenses/NOTICE
awslabs_aws_pricing_mcp_server-1.0.22.dist-info/RECORD
